<?xml version="1.0" encoding="UTF-8"?>
<!DOCTYPE plist PUBLIC "-//Apple//DTD PLIST 1.0//EN" "http://www.apple.com/DTDs/PropertyList-1.0.dtd"/>

<plist version="1.0">
    <dict>
        <key>ROOT</key>
        <array>
            <dict>
                <key>id</key>
                <string>108</string>
                <key>Image</key>
                <dict>
                    <key>value</key>
                    <string>103</string>
                </dict>
            </dict>
            <dict>
                <key>id</key>
                <string>121</string>
                <key>Image</key>
                <dict>
                    <key>value</key>
                    <string>116</string>
                </dict>
            </dict>
            <dict>
                <key>id</key>
                <string>142</string>
                <key>Image</key>
                <dict>
                    <key>value</key>
                    <string>137</string>
                </dict>
            </dict>
            <dict>
                <key>id</key>
                <string>153</string>
                <key>Image</key>
                <dict>
                    <key>value</key>
                    <string>148</string>
                </dict>
            </dict>
            <dict>
                <key>id</key>
                <string>164</string>
                <key>Image</key>
                <dict>
                    <key>value</key>
                    <string>159</string>
                </dict>
            </dict>
            <dict>
                <key>id</key>
                <string>175</string>
                <key>Image</key>
                <dict>
                    <key>value</key>
                    <string>170</string>
                </dict>
            </dict>
            <dict>
                <key>id</key>
                <string>186</string>
                <key>Image</key>
                <dict>
                    <key>value</key>
                    <string>181</string>
                </dict>
            </dict>
            <dict>
                <key>id</key>
                <string>197</string>
                <key>Image</key>
                <dict>
                    <key>value</key>
                    <string>192</string>
                </dict>
            </dict>
            <dict>
                <key>id</key>
                <string>208</string>
                <key>Image</key>
                <dict>
                    <key>value</key>
                    <string>203</string>
                </dict>
            </dict>
            <dict>
                <key>id</key>
                <string>260</string>
                <key>Image</key>
                <dict>
                    <key>value</key>
                    <string>255</string>
                </dict>
            </dict>
            <dict>
                <key>id</key>
                <string>272</string>
                <key>Image</key>
                <dict>
                    <key>value</key>
                    <string>267</string>
                </dict>
            </dict>
            <dict>
                <key>id</key>
                <string>283</string>
                <key>Image</key>
                <dict>
                    <key>value</key>
                    <string>278</string>
                </dict>
            </dict>
            <dict>
                <key>id</key>
                <string>298</string>
                <key>Image</key>
                <dict>
                    <key>value</key>
                    <string>293</string>
                </dict>
            </dict>
            <dict>
                <key>id</key>
                <string>310</string>
                <key>Image</key>
                <dict>
                    <key>value</key>
                    <string>305</string>
                </dict>
            </dict>
            <dict>
                <key>id</key>
                <string>783</string>
                <key>Image</key>
                <dict>
                    <key>value</key>
                    <string>778</string>
                </dict>
            </dict>
            <dict>
                <key>id</key>
                <string>794</string>
                <key>Image</key>
                <dict>
                    <key>value</key>
                    <string>789</string>
                </dict>
            </dict>
            <dict>
                <key>id</key>
                <string>1322</string>
                <key>Image</key>
                <dict>
                    <key>value</key>
                    <string>1317</string>
                </dict>
            </dict>
            <dict>
                <key>id</key>
                <string>1438</string>
                <key>Image</key>
                <dict>
                    <key>value</key>
                    <string>1433</string>
                </dict>
            </dict>
            <dict>
                <key>id</key>
                <string>2076</string>
                <key>Image</key>
                <dict>
                    <key>value</key>
                    <string>2071</string>
                </dict>
            </dict>
            <dict>
                <key>id</key>
                <string>2087</string>
                <key>Image</key>
                <dict>
                    <key>value</key>
                    <string>2082</string>
                </dict>
            </dict>
            <dict>
                <key>id</key>
                <string>4135</string>
                <key>Image</key>
                <dict>
                    <key>value</key>
                    <string>4130</string>
                </dict>
            </dict>
            <dict>
                <key>id</key>
                <string>6850</string>
                <key>Image</key>
                <dict>
                    <key>value</key>
                    <string>6846</string>
                </dict>
            </dict>
            <dict>
                <key>id</key>
                <string>6855</string>
                <key>Image</key>
                <dict>
                    <key>value</key>
                    <string>6851</string>
                </dict>
            </dict>
            <dict>
                <key>id</key>
                <string>6863</string>
                <key>Image</key>
                <dict>
                    <key>value</key>
                    <string>6859</string>
                </dict>
            </dict>
            <dict>
                <key>id</key>
                <string>6891</string>
                <key>Image</key>
                <dict>
                    <key>value</key>
                    <string>6887</string>
                </dict>
            </dict>
            <dict>
                <key>id</key>
                <string>6989</string>
                <key>Image</key>
                <dict>
                    <key>value</key>
                    <string>6985</string>
                </dict>
            </dict>
            <dict>
                <key>id</key>
                <string>7005</string>
                <key>Image</key>
                <dict>
                    <key>value</key>
                    <string>7001</string>
                </dict>
            </dict>
            <dict>
                <key>id</key>
                <string>7089</string>
                <key>Image</key>
                <dict>
                    <key>value</key>
                    <string>7085</string>
                </dict>
            </dict>
            <dict>
                <key>id</key>
                <string>7365</string>
                <key>Image</key>
                <dict>
                    <key>value</key>
                    <string>7361</string>
                </dict>
            </dict>
            <dict>
                <key>id</key>
                <string>8198</string>
                <key>Image</key>
                <dict>
                    <key>value</key>
                    <string>8194</string>
                </dict>
            </dict>
            <dict>
                <key>id</key>
                <string>8306</string>
                <key>Image</key>
                <dict>
                    <key>value</key>
                    <string>8300</string>
                </dict>
            </dict>
            <dict>
                <key>id</key>
                <string>8535</string>
                <key>Image</key>
                <dict>
                    <key>value</key>
                    <string>8530</string>
                </dict>
            </dict>
        </array>
    </dict>
</plist>
